pyfed/__init__.py
pyfed/components.py
pyfed/experiment.py
pyfed/global_var.py
pyfed/ml_socket.py
pyfed_macos-0.0.35.dist-info/METADATA
pyfed_macos-0.0.35.dist-info/WHEEL
pyfed_macos-0.0.35.dist-info/licenses/LICENSE
pyfed_macos-0.0.35.dist-info/RECORD
